GithubStat/__init__.py
GithubStat-1.2.dist-info/LICENSE
GithubStat-1.2.dist-info/METADATA
GithubStat-1.2.dist-info/WHEEL
GithubStat-1.2.dist-info/entry_points.txt
GithubStat-1.2.dist-info/top_level.txt
GithubStat-1.2.dist-info/zip-safe
GithubStat-1.2.dist-info/RECORD
